tempita/__init__.py
tempita/__main__.py
tempita/_looper.py
tempita/compat3.py
tempita_hotoffthehamster-1.0.3.dist-info/LICENSE
tempita_hotoffthehamster-1.0.3.dist-info/METADATA
tempita_hotoffthehamster-1.0.3.dist-info/WHEEL
tempita_hotoffthehamster-1.0.3.dist-info/RECORD
